yktotp/__init__.py
yktotp/__main__.py
yktotp/error.py
yktotp/lib.py
yktotp/password.py
yktotp/tool.py
yktotp/totp.py
yktotp/yk.py
yk_totp-0.2.2.dist-info/LICENSE
yk_totp-0.2.2.dist-info/METADATA
yk_totp-0.2.2.dist-info/WHEEL
yk_totp-0.2.2.dist-info/entry_points.txt
yk_totp-0.2.2.dist-info/top_level.txt
yk_totp-0.2.2.dist-info/RECORD
