Metadata-Version: 2.1
Name: yk-totp
Version: 0.2.2
Summary: A CLI tool to generate TOTP values from a password protected YubiKey by storing the password in the system-protected keyring.
Home-page: https://github.com/cimnine/yk-totp
Author: Christian Mäder
Author-email: yktotp@cimnine.ch
License: BSD 3-Clause License
Platform: UNKNOWN
Classifier: Development Status :: 4 - Beta
Classifier: Environment :: Console
Classifier: Intended Audience :: Developers
Classifier: Intended Audience :: System Administrators
Classifier: License :: OSI Approved :: MIT License
Classifier: Natural Language :: English
Classifier: Operating System :: MacOS :: MacOS X
Classifier: Operating System :: Microsoft :: Windows
Classifier: Operating System :: POSIX
Classifier: Programming Language :: Python :: 3
Classifier: Topic :: Security
Classifier: Topic :: Software Development
Classifier: Topic :: System :: Operating System
Classifier: Topic :: Utilities
Requires-Python: >=3.6
License-File: LICENSE
Requires-Dist: click (>=7.1.2)
Requires-Dist: keyring (>=21.8.0)
Requires-Dist: yubikey-manager (>=4.0.0)
